dbpack/__init__.py
dbpack/database.py
dbpack/printcolors.py
dbpack/sqlite_functions.py
dbpack/version.py
dbpack-1.0.0.data/scripts/selection_columns.py
dbpack-1.0.0.dist-info/LICENSE
dbpack-1.0.0.dist-info/METADATA
dbpack-1.0.0.dist-info/WHEEL
dbpack-1.0.0.dist-info/top_level.txt
dbpack-1.0.0.dist-info/RECORD
