Metadata-Version: 2.1
Name: dbpack
Version: 1.0.0
Summary: UNKNOWN
Home-page: UNKNOWN
Author: Maximilien Lehujeur
Author-email: maximilien.lehujeur@univ-eiffel.fr
License: MIT
Platform: UNKNOWN
Classifier: Programming Language :: Python :: 3
Classifier: Operating System :: POSIX :: Linux
Requires-Python: >=3.7
License-File: LICENSE
Requires-Dist: numpy
